{
	"success": "Complete",
	"failed": "Failed",
	"inWork": "In Work",
	"waiting": "Waiting",
	"rePushWebserviceResponceMessage_success": "JSON Format Validation Completed",
	"rePushWebserviceResponceMessage_failed": "JSON Format Validation Failed",
	"headersForAllInOneTab": [{
			"text": "Sr. No.",
			"value": "sno",
			"width": "92px"
		},
		{
			"text": "Name",
			"align": "start",
			"value": "BOMComponentName"
		},
		{
			"text": "Status",
			"value": "status"
		},
		{
			"text": "Revision",
			"value": "revision"
		},
		{
			"text": "Title",
			"value": "Title"
		},
		{
			"text": "Maturity",
			"value": "maturity"
		},
		{
			"text": "Description",
			"value": "description"
		},
		{
			"text": "CA completed time",
			"value": "caCompletedTime"
		},
		{
			"text": "CA Name",
			"value": "caName"
		},
		{
			"text": "SAP Feedback Time Stamp",
			"value": "SapFeedbackTimeStamp"
		},
		{
			"text": "SAP Feedback Message",
			"value": "SapFeedbackMessage"
		}
	],
	"headersForSeperateTab": [{
			"text": "Sr. No.",
			"value": "sno",
			"width": "92px"
		},
		{
			"text": "Name",
			"align": "start",
			"value": "BOMComponentName"
		},
		{
			"text": "Revision",
			"value": "revision"
		},
		{
			"text": "Title",
			"value": "Title"
		},
		{
			"text": "Maturity",
			"value": "maturity"
		},
		{
			"text": "Description",
			"value": "description"
		},
		{
			"text": "CA completed time",
			"value": "caCompletedTime"
		},
		{
			"text": "CA Name",
			"value": "caName"
		},
		{
			"text": "SAP Feedback Time Stamp",
			"value": "SapFeedbackTimeStamp"
		},
		{
			"text": "SAP Feedback Message",
			"value": "SapFeedbackMessage"
		}
	]
}